Workbook
Name holidays: Holidays!$A$2:$A$937
Name IQ_CH: 110000
Name IQ_CQ: 5000
Name IQ_CY: 10000
Name IQ_DAILY: 500000
Name IQ_FH: 100000
Name IQ_FQ: 500
Name IQ_FY: 1000
Name IQ_LTM: 2000
Name IQ_MONTH: 15000
Name IQ_NTM: 6000
Name IQ_WEEK: 50000
Name IQ_YTD: 3000

Sheet Summary
A5: x | B5: Dates | E5: 46022 | F5: 46112 | G5: =+EOMONTH(F5,1) -> 46142 | H5: =+EOMONTH(G5,1) -> 46173 | I5: =+EOMONTH(H5,1) -> 46203 | J5: =+EOMONTH(I5,1) -> 46234 | K5: =+EOMONTH(J5,1) -> 46265 | L5: =+EOMONTH(K5,1) -> 46295 | M5: =+EOMONTH(L5,1) -> 46326 | N5: =+EOMONTH(M5,1) -> 46356 | ... EG5: =+EOMONTH(EF5,1) -> 50099
B6: Year | C6: [ - ] | F6: =+YEAR(F5) -> 2026 | G6: =+YEAR(G5) -> 2026 | H6: =+YEAR(H5) -> 2026 | I6: =+YEAR(I5) -> 2026 | J6: =+YEAR(J5) -> 2026 | K6: =+YEAR(K5) -> 2026 | L6: =+YEAR(L5) -> 2026 | M6: =+YEAR(M5) -> 2026 | ... EG6: =+YEAR(EG5) -> 2037
B7: CDI | C7: [% p.m.] | G7: =+INDEX(Macro!$C:$C,MATCH(G$5,Macro!$B:$B,0)) -> 0.011435906 | H7: =+INDEX(Macro!$C:$C,MATCH(H$5,Macro!$B:$B,0)) -> 0.011318174 | I7: =+INDEX(Macro!$C:$C,MATCH(I$5,Macro!$B:$B,0)) -> 0.011237146 | J7: =+INDEX(Macro!$C:$C,MATCH(J$5,Macro!$B:$B,0)) -> 0.011141293 | K7: =+INDEX(Macro!$C:$C,MATCH(K$5,Macro!$B:$B,0)) -> 0.011037955 | L7: =+INDEX(Macro!$C:$C,MATCH(L$5,Macro!$B:$B,0)) -> 0.010949286 | M7: =+INDEX(Macro!$C:$C,MATCH(M$5,Macro!$B:$B,0)) -> 0.010867932 | N7: =+INDEX(Macro!$C:$C,MATCH(N$5,Macro!$B:$B,0)) -> 0.010801316 | ... EG7: =+INDEX(Macro!$C:$C,MATCH(EG$5,Macro!$B:$B,0)) -> 0.010727241
B8: =B7 & " Factor" -> CDI Factor | C8: [ - ] | F8: 1 | G8: =+F8*(1+G7) -> 1.0114359 | H8: =+G8*(1+H7) -> 1.0228835 | I8: =+H8*(1+I7) -> 1.0343778 | J8: =+I8*(1+J7) -> 1.0459021 | K8: =+J8*(1+K7) -> 1.0574467 | L8: =+K8*(1+L7) -> 1.069025 | M8: =+L8*(1+M7) -> 1.0806431 | N8: =+M8*(1+N7) -> 1.0923155 | ... EG8: =+EF8*(1+EG7) -> 3.9963239
B9: IPCA | C9: [% p.m.] | G9: =+(1+INDEX(Macro!$F:$F,MATCH(G5,Macro!$B:$B,0)))^(1/12)-1 -> 0.0032716496 | H9: =+(1+INDEX(Macro!$F:$F,MATCH(H5,Macro!$B:$B,0)))^(1/12)-1 -> 0.0032716496 | I9: =+(1+INDEX(Macro!$F:$F,MATCH(I5,Macro!$B:$B,0)))^(1/12)-1 -> 0.0032716496 | J9: =+(1+INDEX(Macro!$F:$F,MATCH(J5,Macro!$B:$B,0)))^(1/12)-1 -> 0.0036706473 | K9: =+(1+INDEX(Macro!$F:$F,MATCH(K5,Macro!$B:$B,0)))^(1/12)-1 -> 0.0036706473 | L9: =+(1+INDEX(Macro!$F:$F,MATCH(L5,Macro!$B:$B,0)))^(1/12)-1 -> 0.0036706473 | M9: =+(1+INDEX(Macro!$F:$F,MATCH(M5,Macro!$B:$B,0)))^(1/12)-1 -> 0.0036706473 | N9: =+(1+INDEX(Macro!$F:$F,MATCH(N5,Macro!$B:$B,0)))^(1/12)-1 -> 0.003851442 | ... CB9: =+(1+INDEX(Macro!$F:$F,MATCH(CB5,Macro!$B:$B,0)))^(1/12)-1 -> 0.0048108117 | CC9: =+CB9 -> 0.0048108117 | CD9: =+CC9 -> 0.0048108117 | CE9: =+CD9 -> 0.0048108117 | CF9: =+CE9 -> 0.0048108117 | CG9: =+CF9 -> 0.0048108117 | CH9: =+CG9 -> 0.0048108117 | CI9: =+CH9 -> 0.0048108117 | CJ9: =+CI9 -> 0.0048108117 | ... EG9: =+EF9 -> 0.0048108117
B10: =B9 & " Factor" -> IPCA Factor | C10: [ - ] | F10: 1 | G10: =+F10*(1+G9) -> 1.0032716 | H10: =+G10*(1+H9) -> 1.006554 | I10: =+H10*(1+I9) -> 1.0098471 | J10: =+I10*(1+J9) -> 1.0135539 | K10: =+J10*(1+K9) -> 1.0172743 | L10: =+K10*(1+L9) -> 1.0210083 | M10: =+L10*(1+M9) -> 1.0247561 | N10: =+M10*(1+N9) -> 1.0287029 | ... EG10: =+EF10*(1+EG9) -> 1.8066002
B11: Selic | C11: [% p.m.] | G11: =+G7 -> 0.011435906 | H11: =+H7 -> 0.011318174 | I11: =+I7 -> 0.011237146 | J11: =+J7 -> 0.011141293 | K11: =+K7 -> 0.011037955 | L11: =+L7 -> 0.010949286 | M11: =+M7 -> 0.010867932 | N11: =+N7 -> 0.010801316 | ... EG11: =+EG7 -> 0.010727241
B12: =B11 & " Factor" -> Selic Factor | C12: [ - ] | F12: 1 | G12: =+F12+G11 -> 1.0114359 | H12: =+G12+H11 -> 1.0227541 | I12: =+H12+I11 -> 1.0339912 | J12: =+I12+J11 -> 1.0451325 | K12: =+J12+K11 -> 1.0561705 | L12: =+K12+L11 -> 1.0671198 | M12: =+L12+M11 -> 1.0779877 | N12: =+M12+N11 -> 1.088789 | ... EG12: =+EF12+EG11 -> 2.3927285
A15: x | B15: Control Panel / Outputs
B18: Deal Level Assumptions | F18: =B133 -> Returns Summary | H18: =C133 -> FIDC | I18: =D133 -> Debtor | J18: =E133 -> CET | P18: FIDC | Debtor | CET IRR %
F19: =B134 -> IRR % | H19: =C134 -> 0.28011814 | I19: =D134 -> 0.29647614 | J19: =E134 -> 0.35930123 | P19: Check Size R$ k
B20: Disbursement to Debtor, Gross of Taxes | C20: [R$ k] | D20: =+I29 -> 45 | F20: =B135 -> IRR IPCA + % | H20: =C135 -> 0.22258845 | I20: =D135 -> 0.23823712 | J20: =E135 -> 0.29824005 | O20: =TEXT(C134,"0.0%")&" | "&TEXT(D134,"0.0%")&" | "&TEXT(E134,"0.0%") -> 28.0% | 29.6% | 35.9% | P20: 30 | Q20: =+($T$31-$P$31)/4+P20 -> 37.5 | R20: =+($T$31-$P$31)/4+Q20 -> 45 | S20: =+($T$31-$P$31)/4+R20 -> 52.5 | T20: 60
B21: Total Debt | C21: [R$ k] | D21: =+F180 -> 49.473334 | F21: =B136 -> IRR CDI + % | H21: =C136 -> 0.12720175 | I21: =D136 -> 0.14157296 | J21: =E136 -> 0.19689171 | O21: 12 | P21: 26.9% | 29.7% | 42.6% | Q21: 27.5% | 29.7% | 42.6% | R21: 27.8% | 29.7% | 42.6% | S21: 28.1% | 29.7% | 42.6% | T21: 28.3% | 29.7% | 42.6%
B22: Attachment Point LTV | C22: [%] | D22: 0.3 | F22: =B137 -> MOICx | H22: =C137 -> 1.6291691 | I22: =D137 -> 1.6820465 | J22: =E137 -> 1.8492544 | O22: =+O21+12 -> 24 | P22: 27.2% | 29.6% | 35.9% | Q22: 27.7% | 29.6% | 35.9% | R22: 28.0% | 29.6% | 35.9% | S22: 28.2% | 29.6% | 35.9% | T22: 28.4% | 29.6% | 35.9%
F23: =B138 -> Duration Yrs | H23: =C138 -> 1.9763736 | I23: =D138 -> 2.0027397 | J23: =E138 -> 2.0027397 | N23: Time to Settle | O23: =+O22+12 -> 36 | P23: 27.5% | 29.7% | 33.8% | Q23: 27.9% | 29.7% | 33.8% | R23: 28.2% | 29.7% | 33.8% | S23: 28.4% | 29.7% | 33.8% | T23: 28.6% | 29.7% | 33.8%
B24: Interest | F24: =B139 -> Gains R$ mm | H24: =C139 -> 32.111115 | I24: =D139 -> 33.743115 | J24: =E139 -> 38.21645 | N24: # months | O24: =+O23+12 -> 48 | P24: 27.7% | 29.7% | 32.8% | Q24: 28.1% | 29.7% | 32.8% | R24: 28.4% | 29.7% | 32.8% | S24: 28.6% | 29.7% | 32.8% | T24: 28.7% | 29.7% | 32.8%
B25: Annual Basis | C25: [% p.a.] | D25: =+I49 -> 0.29693736 | O25: =+O24+12 -> 60 | P25: 27.9% | 29.7% | 32.2% | Q25: 28.3% | 29.7% | 32.2% | R25: 28.5% | 29.7% | 32.2% | S25: 28.7% | 29.7% | 32.2% | T25: 28.8% | 29.7% | 32.2%
B26: Semiannual Basis | C26: [% p.s.] | D26: =+(1+D$25)^(1/2)-1 -> 0.13883158 | O26: =+O25+12 -> 72 | P26: 26.5% | 28.1% | 30.1% | Q26: 26.8% | 28.1% | 30.1% | R26: 27.0% | 28.1% | 30.1% | S26: 27.2% | 28.1% | 30.1% | T26: 27.3% | 28.1% | 30.1%
B27: Quarterly Basis | C27: [% p.q.] | D27: =+(1+D$25)^(1/4)-1 -> 0.067160521 | F27: Inputs Calculadora
B28: Monthly Basis | C28: [% p.m.] | D28: =+(1+D$25)^(1/12)-1 -> 0.021903571
F29: Valor do Crédito | H29: [R$ k] | I29: 45 | P29: FIDC | Debtor | CET IRR CDI + %
B30: Upfront Fees | F30: Pagamento de Juros | H30: {=+_xlfn.IFS(I30="Coupon",1,I30="Bullet",2)} -> 2 | I30: Bullet | P30: Check Size R$ k
B31: Lawyer Origination Fee | C31: [%] | D31: 0.03 | F31: Parcelas | H31: {=+_xlfn.IFS(I31="Mensal",1,I31="Trimestral",2,I31="Semestral",3,I31="Anual",4)} -> 1 | I31: Mensal | O31: =TEXT(C136,"0.0%")&" | "&TEXT(D136,"0.0%")&" | "&TEXT(E136,"0.0%") -> 12.7% | 14.2% | 19.7% | P31: 30 | Q31: =+($T$31-$P$31)/4+P31 -> 37.5 | R31: =+($T$31-$P$31)/4+Q31 -> 45 | S31: =+($T$31-$P$31)/4+R31 -> 52.5 | T31: 60
B32: BT Closing Fee | C32: [%] | D32: 0.03 | F32: Prazo (meses) | H32: {=+_xlfn.IFS(I32=12,1,I32=18,2,I32=24,3,I32=30,4,I32=36,5)} -> 3 | I32: 24 | O32: 12 | P32: 11.4% | 13.8% | 25.1% | Q32: 11.9% | 13.8% | 25.1% | R32: 12.2% | 13.8% | 25.1% | S32: 12.4% | 13.8% | 25.1% | T32: 12.6% | 13.8% | 25.1%
B33: Bank Issuance Fee | O33: 24 | P33: 12.0% | 14.2% | 19.7% | Q33: 12.4% | 14.2% | 19.7% | R33: 12.7% | 14.2% | 19.7% | S33: 12.9% | 14.2% | 19.7% | T33: 13.1% | 14.2% | 19.7%
B34: % flat | C34: [%] | D34: 0.0045 | N34: Time to Settle | O34: 36 | P34: 12.4% | 14.3% | 18.0% | Q34: 12.8% | 14.3% | 18.0% | R34: 13.0% | 14.3% | 18.0% | S34: 13.2% | 14.3% | 18.0% | T34: 13.3% | 14.3% | 18.0%
B35: Minimum Value | C35: [R$ k] | D35: =2*0 -> 0 | F35: Interest Build-Up | N35: # months | O35: 48 | P35: 12.6% | 14.3% | 17.1% | Q35: 13.0% | 14.3% | 17.1% | R35: 13.2% | 14.3% | 17.1% | S35: 13.4% | 14.3% | 17.1% | T35: 13.5% | 14.3% | 17.1%
O36: 60 | P36: 12.8% | 14.3% | 16.5% | Q36: 13.1% | 14.3% | 16.5% | R36: 13.3% | 14.3% | 16.5% | S36: 13.5% | 14.3% | 16.5% | T36: 13.6% | 14.3% | 16.5%
B37: Upfront Operational Costs | F37: Juros Base | H37: [% p.a.] | I37: 0.267 | J37: [% p.m.] | K37: =+(1+I37)^(1/12)-1 -> 0.019916735 | O37: 72 | P37: 11.5% | 12.9% | 14.7% | Q37: 11.8% | 12.9% | 14.7% | R37: 12.0% | 12.9% | 14.7% | S37: 12.1% | 12.9% | 14.7% | T37: 12.2% | 12.9% | 14.7%
B38: Escrow Opening Fee | C38: [R$ k] | D38: 0 | F38: Juros Teto | H38: [% p.a.] | I38: 0.33582152 | J38: [% p.m.] | K38: =+(1+I38)^(1/12)-1 -> 0.02442233
B39: RTD Register | C39: [R$ k] | D39: =+_xlfn.XLOOKUP(D20*10^3,'Comparativo RTD'!$B$10:$B$19,'Comparativo RTD'!$I$10:$I$19,,1)/10^3*0 -> 0
F40: Pagamento de Juros | H40: [% p.a.] | I40: =+($I$38-$I$37)*60% -> 0.041292912 | J40: [% p.m.] | K40: =+(1+I40)^(1/12)-1 -> 0.0033776185
B41: Recurring Operational Costs | F41: Ajustado c/ Switch | H41: [% p.a.] | I41: =$H30/4*I40 -> 0.020646456 | J41: [% p.m.] | K41: =$H30/4*K40 -> 0.0016888092
B42: Escrow Monthly Fee | C42: [R$ k/month] | D42: =68/10^3*1 -> 0.068
F43: Parcelas | H43: [% p.a.] | I43: =+($I$38-$I$37)*30% -> 0.020646456 | J43: [% p.m.] | K43: =+(1+I43)^(1/12)-1 -> 0.0017044682
B44: Taxes | F44: Ajustado c/ Switch | H44: [% p.a.] | I44: =$H31/4*I43 -> 0.005161614 | J44: [% p.m.] | K44: =$H31/4*K43 -> 0.00042611705
B45: IOF on Issuance | C45: [%] | D45: 0.03373
F46: Prazo (meses) | H46: [% p.a.] | I46: =+($I$38-$I$37)*10% -> 0.006882152 | J46: [% p.m.] | K46: =+(1+I46)^(1/12)-1 -> 0.00057171154
B47: Realization | F47: Ajustado c/ Switch | H47: [% p.a.] | I47: =$H32/5*I46 -> 0.0041292912 | J47: [% p.m.] | K47: =$H32/5*K46 -> 0.00034302692
B48: Time to Settle | C48: [# months] | D48: =+I32 -> 24
B49: PDD | C49: [%] | D49: 0 | F49: Total (Debtor) | H49: [% p.a.] | I49: =+I37+I41+I44+I47 -> 0.29693736 | J49: [% p.m.] | K49: =+(1+I49)^(1/12)-1 -> 0.021903571
B50: Delay on Realization | C50: [# months] | D50: 0 | F50: Total (CET) | H50: [% p.a.] | I50: =+J19 -> 0.35930123 | J50: [% p.m.] | K50: =+(1+I50)^(1/12)-1 -> 0.025910896
B52: Credit Assumptions | F52: Installments Schedule R$
B54: Monetary Adjustment | C54: {=+_xlfn.IFS(D54="IPCA",1,D54="None",2)} -> 1 | D54: IPCA | G54: Interest | H54: Amortization | I54: Total
B55: Interest | F55: 1 | G55: =-SUMIFS($177:$177,$100:$100,F55)*10^3 -> 0 | H55: =-SUMIFS($178:$178,$100:$100,F55)*10^3 -> 0 | I55: =+SUM(G55:H55) -> 0
B56: 1st Threshold | F56: =+F55+1 -> 2 | G56: =-SUMIFS($177:$177,$100:$100,F56)*10^3 -> 0 | H56: =-SUMIFS($178:$178,$100:$100,F56)*10^3 -> 0 | I56: =+SUM(G56:H56) -> 0
B57: Date Limit | C57: [# months] | D57: 24 | F57: =+F56+1 -> 3 | G57: =-SUMIFS($177:$177,$100:$100,F57)*10^3 -> 0 | H57: =-SUMIFS($178:$178,$100:$100,F57)*10^3 -> 0 | I57: =+SUM(G57:H57) -> 0
B58: Interest | C58: [% p.a., linear] | D58: 0 | F58: =+F57+1 -> 4 | G58: =-SUMIFS($177:$177,$100:$100,F58)*10^3 -> 0 | H58: =-SUMIFS($178:$178,$100:$100,F58)*10^3 -> 0 | I58: =+SUM(G58:H58) -> 0
B59: 2nd Threshold | F59: =+F58+1 -> 5 | G59: =-SUMIFS($177:$177,$100:$100,F59)*10^3 -> 0 | H59: =-SUMIFS($178:$178,$100:$100,F59)*10^3 -> 0 | I59: =+SUM(G59:H59) -> 0
B60: Date Limit | C60: [# months] | D60: 24 | F60: =+F59+1 -> 6 | G60: =-SUMIFS($177:$177,$100:$100,F60)*10^3 -> 0 | H60: =-SUMIFS($178:$178,$100:$100,F60)*10^3 -> 0 | I60: =+SUM(G60:H60) -> 0
B61: Interest | C61: [% p.a., linear] | D61: 0.02 | F61: =+F60+1 -> 7 | G61: =-SUMIFS($177:$177,$100:$100,F61)*10^3 -> 0 | H61: =-SUMIFS($178:$178,$100:$100,F61)*10^3 -> 0 | I61: =+SUM(G61:H61) -> 0
F62: =+F61+1 -> 8 | G62: =-SUMIFS($177:$177,$100:$100,F62)*10^3 -> 0 | H62: =-SUMIFS($178:$178,$100:$100,F62)*10^3 -> 0 | I62: =+SUM(G62:H62) -> 0
B63: Switches | F63: =+F62+1 -> 9 | G63: =-SUMIFS($177:$177,$100:$100,F63)*10^3 -> 0 | H63: =-SUMIFS($178:$178,$100:$100,F63)*10^3 -> 0 | I63: =+SUM(G63:H63) -> 0
F64: =+F63+1 -> 10 | G64: =-SUMIFS($177:$177,$100:$100,F64)*10^3 -> 0 | H64: =-SUMIFS($178:$178,$100:$100,F64)*10^3 -> 0 | I64: =+SUM(G64:H64) -> 0
B65: Costs Allocation | F65: =+F64+1 -> 11 | G65: =-SUMIFS($177:$177,$100:$100,F65)*10^3 -> 0 | H65: =-SUMIFS($178:$178,$100:$100,F65)*10^3 -> 0 | I65: =+SUM(G65:H65) -> 0
B66: Lawyer Origination Fee | C66: {=+_xlfn.IFS(D66="Debtors",1,D66="FIDC",2)} -> 1 | D66: Debtors | F66: =+F65+1 -> 12 | G66: =-SUMIFS($177:$177,$100:$100,F66)*10^3 -> 0 | H66: =-SUMIFS($178:$178,$100:$100,F66)*10^3 -> 0 | I66: =+SUM(G66:H66) -> 0
B67: BT Closing Fee | C67: {=+_xlfn.IFS(D67="Debtors",1,D67="FIDC",2)} -> 1 | D67: Debtors | F67: =+F66+1 -> 13 | G67: =-SUMIFS($177:$177,$100:$100,F67)*10^3 -> 0 | H67: =-SUMIFS($178:$178,$100:$100,F67)*10^3 -> 0 | I67: =+SUM(G67:H67) -> 0
B68: Bank Issuance Fee | C68: {=+_xlfn.IFS(D68="Debtors",1,D68="FIDC",2)} -> 1 | D68: Debtors | F68: =+F67+1 -> 14 | G68: =-SUMIFS($177:$177,$100:$100,F68)*10^3 -> 0 | H68: =-SUMIFS($178:$178,$100:$100,F68)*10^3 -> 0 | I68: =+SUM(G68:H68) -> 0
F69: =+F68+1 -> 15 | G69: =-SUMIFS($177:$177,$100:$100,F69)*10^3 -> 0 | H69: =-SUMIFS($178:$178,$100:$100,F69)*10^3 -> 0 | I69: =+SUM(G69:H69) -> 0
F70: =+F69+1 -> 16 | G70: =-SUMIFS($177:$177,$100:$100,F70)*10^3 -> 0 | H70: =-SUMIFS($178:$178,$100:$100,F70)*10^3 -> 0 | I70: =+SUM(G70:H70) -> 0
F71: =+F70+1 -> 17 | G71: =-SUMIFS($177:$177,$100:$100,F71)*10^3 -> 0 | H71: =-SUMIFS($178:$178,$100:$100,F71)*10^3 -> 0 | I71: =+SUM(G71:H71) -> 0
F72: =+F71+1 -> 18 | G72: =-SUMIFS($177:$177,$100:$100,F72)*10^3 -> 0 | H72: =-SUMIFS($178:$178,$100:$100,F72)*10^3 -> 0 | I72: =+SUM(G72:H72) -> 0
F73: =+F72+1 -> 19 | G73: =-SUMIFS($177:$177,$100:$100,F73)*10^3 -> 0 | H73: =-SUMIFS($178:$178,$100:$100,F73)*10^3 -> 0 | I73: =+SUM(G73:H73) -> 0
F74: =+F73+1 -> 20 | G74: =-SUMIFS($177:$177,$100:$100,F74)*10^3 -> 0 | H74: =-SUMIFS($178:$178,$100:$100,F74)*10^3 -> 0 | I74: =+SUM(G74:H74) -> 0
F75: =+F74+1 -> 21 | G75: =-SUMIFS($177:$177,$100:$100,F75)*10^3 -> 0 | H75: =-SUMIFS($178:$178,$100:$100,F75)*10^3 -> 0 | I75: =+SUM(G75:H75) -> 0
F76: =+F75+1 -> 22 | G76: =-SUMIFS($177:$177,$100:$100,F76)*10^3 -> 0 | H76: =-SUMIFS($178:$178,$100:$100,F76)*10^3 -> 0 | I76: =+SUM(G76:H76) -> 0
F77: =+F76+1 -> 23 | G77: =-SUMIFS($177:$177,$100:$100,F77)*10^3 -> 0 | H77: =-SUMIFS($178:$178,$100:$100,F77)*10^3 -> 0 | I77: =+SUM(G77:H77) -> 0
F78: =+F77+1 -> 24 | G78: =-SUMIFS($177:$177,$100:$100,F78)*10^3 -> 0 | H78: =-SUMIFS($178:$178,$100:$100,F78)*10^3 -> 83216.45 | I78: =+SUM(G78:H78) -> 83216.45
F79: =+F78+1 -> 25 | G79: =-SUMIFS($177:$177,$100:$100,F79)*10^3 -> 0 | H79: =-SUMIFS($178:$178,$100:$100,F79)*10^3 -> 0 | I79: =+SUM(G79:H79) -> 0
F80: =+F79+1 -> 26 | G80: =-SUMIFS($177:$177,$100:$100,F80)*10^3 -> 0 | H80: =-SUMIFS($178:$178,$100:$100,F80)*10^3 -> 0 | I80: =+SUM(G80:H80) -> 0
... F90: =+F89+1 -> 36 | G90: =-SUMIFS($177:$177,$100:$100,F90)*10^3 -> 0 | H90: =-SUMIFS($178:$178,$100:$100,F90)*10^3 -> 0 | I90: =+SUM(G90:H90) -> 0
F91: Total | G91: =+SUM(G55:G90) -> 0 | H91: =+SUM(H55:H90) -> 83216.45 | I91: =+SUM(I55:I90) -> 83216.45
A100: x | B100: Cash Flow / Projections | F100: 0 | G100: =+F100+1 -> 1 | H100: =+G100+1 -> 2 | I100: =+H100+1 -> 3 | J100: =+I100+1 -> 4 | K100: =+J100+1 -> 5 | L100: =+K100+1 -> 6 | M100: =+L100+1 -> 7 | N100: =+M100+1 -> 8 | ... EG100: =+EF100+1 -> 131
B102: Cash Flow
B104: (-) Investment | C104: [R$ k] | F104: =+SUM(F105:F108) -> -47.9025 | G104: =+SUM(G105:G108) -> 0 | H104: =+SUM(H105:H108) -> 0 | I104: =+SUM(I105:I108) -> 0 | J104: =+SUM(J105:J108) -> 0 | K104: =+SUM(K105:K108) -> 0 | L104: =+SUM(L105:L108) -> 0 | M104: =+SUM(M105:M108) -> 0 | ... EG104: =+SUM(EG105:EG108) -> 0
B105: Debtor | C105: [R$ k] | F105: =-$D$20*N(F$100=0) -> -45 | G105: =-$D$20*N(G$100=0) -> 0 | H105: =-$D$20*N(H$100=0) -> 0 | I105: =-$D$20*N(I$100=0) -> 0 | J105: =-$D$20*N(J$100=0) -> 0 | K105: =-$D$20*N(K$100=0) -> 0 | L105: =-$D$20*N(L$100=0) -> 0 | M105: =-$D$20*N(M$100=0) -> 0 | ... EG105: =-$D$20*N(EG$100=0) -> 0
B106: =+$B$31 -> Lawyer Origination Fee | C106: [R$ k] | F106: =+$D$31*F105 -> -1.35 | G106: =+$D$31*G105 -> 0 | H106: =+$D$31*H105 -> 0 | I106: =+$D$31*I105 -> 0 | J106: =+$D$31*J105 -> 0 | K106: =+$D$31*K105 -> 0 | L106: =+$D$31*L105 -> 0 | M106: =+$D$31*M105 -> 0 | ... EG106: =+$D$31*EG105 -> 0
B107: =+$B$32 -> BT Closing Fee | C107: [R$ k] | F107: =+$D$32*F105 -> -1.35 | G107: =+$D$32*G105 -> 0 | H107: =+$D$32*H105 -> 0 | I107: =+$D$32*I105 -> 0 | J107: =+$D$32*J105 -> 0 | K107: =+$D$32*K105 -> 0 | L107: =+$D$32*L105 -> 0 | M107: =+$D$32*M105 -> 0 | ... EG107: =+$D$32*EG105 -> 0
B108: =+$B$33 -> Bank Issuance Fee | C108: [R$ k] | F108: =-MAX(-$D$34*F105,$D$35)*N(F$100=0) -> -0.2025 | G108: =-MAX(-$D$34*G105,$D$35)*N(G$100=0) -> 0 | H108: =-MAX(-$D$34*H105,$D$35)*N(H$100=0) -> 0 | I108: =-MAX(-$D$34*I105,$D$35)*N(I$100=0) -> 0 | J108: =-MAX(-$D$34*J105,$D$35)*N(J$100=0) -> 0 | K108: =-MAX(-$D$34*K105,$D$35)*N(K$100=0) -> 0 | L108: =-MAX(-$D$34*L105,$D$35)*N(L$100=0) -> 0 | M108: =-MAX(-$D$34*M105,$D$35)*N(M$100=0) -> 0 | ... EG108: =-MAX(-$D$34*EG105,$D$35)*N(EG$100=0) -> 0
B109: (-) Taxes | C109: [R$ k] | F109: =+SUM(F110) -> -1.5708342 | G109: =+SUM(G110) -> 0 | H109: =+SUM(H110) -> 0 | I109: =+SUM(I110) -> 0 | J109: =+SUM(J110) -> 0 | K109: =+SUM(K110) -> 0 | L109: =+SUM(L110) -> 0 | M109: =+SUM(M110) -> 0 | ... EG109: =+SUM(EG110) -> 0
B110: =+$B$45 -> IOF on Issuance | C110: [R$ k] | F110: =+F105*(1/(1-$D$45)-1) -> -1.5708342 | G110: =+G105*(1/(1-$D$45)-1) -> 0 | H110: =+H105*(1/(1-$D$45)-1) -> 0 | I110: =+I105*(1/(1-$D$45)-1) -> 0 | J110: =+J105*(1/(1-$D$45)-1) -> 0 | K110: =+K105*(1/(1-$D$45)-1) -> 0 | L110: =+L105*(1/(1-$D$45)-1) -> 0 | M110: =+M105*(1/(1-$D$45)-1) -> 0 | ... EG110: =+EG105*(1/(1-$D$45)-1) -> 0
B111: (-) Investment Expenses | C111: [R$ k] | F111: =+SUM(F112:F114) -> 0 | G111: =+SUM(G112:G114) -> -0.068 | H111: =+SUM(H112:H114) -> -0.068 | I111: =+SUM(I112:I114) -> -0.068 | J111: =+SUM(J112:J114) -> -0.068 | K111: =+SUM(K112:K114) -> -0.068 | L111: =+SUM(L112:L114) -> -0.068 | M111: =+SUM(M112:M114) -> -0.068 | ... EG111: =+SUM(EG112:EG114) -> 0
B112: =+$B$38 -> Escrow Opening Fee | C112: [R$ k] | F112: =-$D$38*N(F$100=0) -> 0 | G112: =-$D$38*N(G$100=0) -> 0 | H112: =-$D$38*N(H$100=0) -> 0 | I112: =-$D$38*N(I$100=0) -> 0 | J112: =-$D$38*N(J$100=0) -> 0 | K112: =-$D$38*N(K$100=0) -> 0 | L112: =-$D$38*N(L$100=0) -> 0 | M112: =-$D$38*N(M$100=0) -> 0 | ... EG112: =-$D$38*N(EG$100=0) -> 0
B113: =+$B$39 -> RTD Register | C113: [R$ k] | F113: =-$D$39*N(F$100=0) -> 0 | G113: =-$D$39*N(G$100=0) -> 0 | H113: =-$D$39*N(H$100=0) -> 0 | I113: =-$D$39*N(I$100=0) -> 0 | J113: =-$D$39*N(J$100=0) -> 0 | K113: =-$D$39*N(K$100=0) -> 0 | L113: =-$D$39*N(L$100=0) -> 0 | M113: =-$D$39*N(M$100=0) -> 0 | ... EG113: =-$D$39*N(EG$100=0) -> 0
B114: =+$B$42 -> Escrow Monthly Fee | C114: [R$ k] | F114: =-$D$42*AND(F158>0,F174>0) -> 0 | G114: =-$D$42*AND(G158>0,G174>0) -> -0.068 | H114: =-$D$42*AND(H158>0,H174>0) -> -0.068 | I114: =-$D$42*AND(I158>0,I174>0) -> -0.068 | J114: =-$D$42*AND(J158>0,J174>0) -> -0.068 | K114: =-$D$42*AND(K158>0,K174>0) -> -0.068 | L114: =-$D$42*AND(L158>0,L174>0) -> -0.068 | M114: =-$D$42*AND(M158>0,M174>0) -> -0.068 | ... EG114: =-$D$42*AND(EG158>0,EG174>0) -> 0
B115: (+) Realization | C115: [R$ k] | F115: =+SUM(F116:F116) -> 0 | G115: =+SUM(G116:G116) -> 0 | H115: =+SUM(H116:H116) -> 0 | I115: =+SUM(I116:I116) -> 0 | J115: =+SUM(J116:J116) -> 0 | K115: =+SUM(K116:K116) -> 0 | L115: =+SUM(L116:L116) -> 0 | M115: =+SUM(M116:M116) -> 0 | ... EG115: =+SUM(EG116:EG116) -> 0
B116: Net of PDD | C116: [R$ k] | F116: =-SUM(F177:F178) -> 0 | G116: =-SUM(G177:G178) -> 0 | H116: =-SUM(H177:H178) -> 0 | I116: =-SUM(I177:I178) -> 0 | J116: =-SUM(J177:J178) -> 0 | K116: =-SUM(K177:K178) -> 0 | L116: =-SUM(L177:L178) -> 0 | M116: =-SUM(M177:M178) -> 0 | ... EG116: =-SUM(EG177:EG178) -> 0
B117: (+) Option Cash Flow | C117: [R$ k] | F117: =+SUM(F118:F119) -> 0 | G117: =+SUM(G118:G119) -> 0 | H117: =+SUM(H118:H119) -> 0 | I117: =+SUM(I118:I119) -> 0 | J117: =+SUM(J118:J119) -> 0 | K117: =+SUM(K118:K119) -> 0 | L117: =+SUM(L118:L119) -> 0 | M117: =+SUM(M118:M119) -> 0 | ... EG117: =+SUM(EG118:EG119) -> 0
B118: Premium Disbursement | C118: [R$ k] | F118: 0 | G118: 0 | H118: 0 | I118: 0 | J118: 0 | K118: 0 | L118: 0 | M118: 0 | N118: 0 | O118: 0 | P118: 0 | Q118: 0 | R118: 0 | S118: 0 | T118: 0 | U118: 0 | V118: 0 | W118: 0 | X118: 0 | Y118: 0 | Z118: 0 | AA118: 0 | AB118: 0 | AC118: 0 | AD118: 0 | AE118: 0 | AF118: 0 | AG118: 0 | AH118: 0 | AI118: 0 | AJ118: 0 | AK118: 0 | AL118: 0 | AM118: 0 | AN118: 0 | AO118: 0 | AP118: 0 | AQ118: 0 | AR118: 0 | AS118: 0 | AT118: 0 | AU118: 0 | AV118: 0 | AW118: 0 | AX118: 0 | AY118: 0 | AZ118: 0 | BA118: 0 | BB118: 0 | BC118: 0 | BD118: 0 | BE118: 0 | BF118: 0 | BG118: 0 | BH118: 0 | BI118: 0 | BJ118: 0 | BK118: 0 | BL118: 0 | BM118: 0 | BN118: 0 | BO118: 0 | BP118: 0 | BQ118: 0 | BR118: 0 | BS118: 0 | BT118: 0 | BU118: 0 | BV118: 0 | BW118: 0 | BX118: 0 | BY118: 0 | BZ118: 0 | CA118: 0 | CB118: 0 | CC118: 0 | CD118: 0 | CE118: 0 | CF118: 0 | CG118: 0 | CH118: 0 | CI118: 0 | CJ118: 0 | CK118: 0 | CL118: 0 | CM118: 0 | CN118: 0 | CO118: 0 | CP118: 0 | CQ118: 0 | CR118: 0 | CS118: 0 | CT118: 0 | CU118: 0 | CV118: 0 | CW118: 0 | CX118: 0 | CY118: 0 | CZ118: 0 | DA118: 0 | DB118: 0 | DC118: 0 | DD118: 0 | DE118: 0 | DF118: 0 | DG118: 0 | DH118: 0 | DI118: 0 | DJ118: 0 | DK118: 0 | DL118: 0 | DM118: 0 | DN118: 0 | DO118: 0 | DP118: 0 | DQ118: 0 | DR118: 0 | DS118: 0 | DT118: 0 | DU118: 0 | DV118: 0 | DW118: 0 | DX118: 0 | DY118: 0 | DZ118: 0 | EA118: 0 | EB118: 0 | EC118: 0 | ED118: 0 | EE118: 0 | EF118: 0 | EG118: 0
B119: Premium Realization | C119: [R$ k] | F119: 0 | G119: 0 | H119: 0 | I119: 0 | J119: 0 | K119: 0 | L119: 0 | M119: 0 | N119: 0 | O119: 0 | P119: 0 | Q119: 0 | R119: 0 | S119: 0 | T119: 0 | U119: 0 | V119: 0 | W119: 0 | X119: 0 | Y119: 0 | Z119: 0 | AA119: 0 | AB119: 0 | AC119: 0 | AD119: 0 | AE119: 0 | AF119: 0 | AG119: 0 | AH119: 0 | AI119: 0 | AJ119: 0 | AK119: 0 | AL119: 0 | AM119: 0 | AN119: 0 | AO119: 0 | AP119: 0 | AQ119: 0 | AR119: 0 | AS119: 0 | AT119: 0 | AU119: 0 | AV119: 0 | AW119: 0 | AX119: 0 | AY119: 0 | AZ119: 0 | BA119: 0 | BB119: 0 | BC119: 0 | BD119: 0 | BE119: 0 | BF119: 0 | BG119: 0 | BH119: 0 | BI119: 0 | BJ119: 0 | BK119: 0 | BL119: 0 | BM119: 0 | BN119: 0 | BO119: 0 | BP119: 0 | BQ119: 0 | BR119: 0 | BS119: 0 | BT119: 0 | BU119: 0 | BV119: 0 | BW119: 0 | BX119: 0 | BY119: 0 | BZ119: 0 | CA119: 0 | CB119: 0 | CC119: 0 | CD119: 0 | CE119: 0 | CF119: 0 | CG119: 0 | CH119: 0 | CI119: 0 | CJ119: 0 | CK119: 0 | CL119: 0 | CM119: 0 | CN119: 0 | CO119: 0 | CP119: 0 | CQ119: 0 | CR119: 0 | CS119: 0 | CT119: 0 | CU119: 0 | CV119: 0 | CW119: 0 | CX119: 0 | CY119: 0 | CZ119: 0 | DA119: 0 | DB119: 0 | DC119: 0 | DD119: 0 | DE119: 0 | DF119: 0 | DG119: 0 | DH119: 0 | DI119: 0 | DJ119: 0 | DK119: 0 | DL119: 0 | DM119: 0 | DN119: 0 | DO119: 0 | DP119: 0 | DQ119: 0 | DR119: 0 | DS119: 0 | DT119: 0 | DU119: 0 | DV119: 0 | DW119: 0 | DX119: 0 | DY119: 0 | DZ119: 0 | EA119: 0 | EB119: 0 | EC119: 0 | ED119: 0 | EE119: 0 | EF119: 0 | EG119: 0
B120: (=) Cash Flow | C120: [R$ k] | F120: =+F104+F109+F111+F115+F117 -> -49.473334 | G120: =+G104+G109+G111+G115+G117 -> -0.068 | H120: =+H104+H109+H111+H115+H117 -> -0.068 | I120: =+I104+I109+I111+I115+I117 -> -0.068 | J120: =+J104+J109+J111+J115+J117 -> -0.068 | K120: =+K104+K109+K111+K115+K117 -> -0.068 | L120: =+L104+L109+L111+L115+L117 -> -0.068 | M120: =+M104+M109+M111+M115+M117 -> -0.068 | ... EG120: =+EG104+EG109+EG111+EG115+EG117 -> 0
B121: IPCA + Cash Flow | C121: [R$ k] | F121: =+F120/F$10 -> -49.473334 | G121: =+G120/G$10 -> -0.067778253 | H121: =+H120/H$10 -> -0.06755723 | I121: =+I120/I$10 -> -0.067336927 | J121: =+J120/J$10 -> -0.067090661 | K121: =+K120/K$10 -> -0.066845295 | L121: =+L120/L$10 -> -0.066600827 | M121: =+M120/M$10 -> -0.066357253 | ... EG121: =+EG120/EG$10 -> 0
B122: CDI + Cash Flow | C122: [R$ k] | F122: =+F120/F$8 -> -49.473334 | G122: =+G120/G$8 -> -0.067231151 | H122: =+H120/H$8 -> -0.066478733 | I122: =+I120/I$8 -> -0.065740003 | J122: =+J120/J$8 -> -0.065015645 | K122: =+K120/K$8 -> -0.06430584 | L122: =+L120/L$8 -> -0.063609363 | M122: =+M120/M$8 -> -0.062925493 | ... EG122: =+EG120/EG$8 -> 0
B124: Gross Debtor Cash Flow | C124: [R$ k] | F124: =+F105+F110+(CHOOSE($C$66,F106,0)+CHOOSE($C$67,F107,0)+CHOOSE($C$68,F108,0))+F115 -> -49.473334 | G124: =+G105+G110+(CHOOSE($C$66,G106,0)+CHOOSE($C$67,G107,0)+CHOOSE($C$68,G108,0))+G115 -> 0 | H124: =+H105+H110+(CHOOSE($C$66,H106,0)+CHOOSE($C$67,H107,0)+CHOOSE($C$68,H108,0))+H115 -> 0 | I124: =+I105+I110+(CHOOSE($C$66,I106,0)+CHOOSE($C$67,I107,0)+CHOOSE($C$68,I108,0))+I115 -> 0 | J124: =+J105+J110+(CHOOSE($C$66,J106,0)+CHOOSE($C$67,J107,0)+CHOOSE($C$68,J108,0))+J115 -> 0 | K124: =+K105+K110+(CHOOSE($C$66,K106,0)+CHOOSE($C$67,K107,0)+CHOOSE($C$68,K108,0))+K115 -> 0 | L124: =+L105+L110+(CHOOSE($C$66,L106,0)+CHOOSE($C$67,L107,0)+CHOOSE($C$68,L108,0))+L115 -> 0 | M124: =+M105+M110+(CHOOSE($C$66,M106,0)+CHOOSE($C$67,M107,0)+CHOOSE($C$68,M108,0))+M115 -> 0 | ... EG124: =+EG105+EG110+(CHOOSE($C$66,EG106,0)+CHOOSE($C$67,EG107,0)+CHOOSE($C$68,EG108,0))+EG115 -> 0
B125: IPCA + Cash Flow | C125: [R$ k] | F125: =+F124/F$10 -> -49.473334 | G125: =+G124/G$10 -> 0 | H125: =+H124/H$10 -> 0 | I125: =+I124/I$10 -> 0 | J125: =+J124/J$10 -> 0 | K125: =+K124/K$10 -> 0 | L125: =+L124/L$10 -> 0 | M125: =+M124/M$10 -> 0 | ... EG125: =+EG124/EG$10 -> 0
B126: CDI + Cash Flow | C126: [R$ k] | F126: =+F124/F$8 -> -49.473334 | G126: =+G124/G$8 -> 0 | H126: =+H124/H$8 -> 0 | I126: =+I124/I$8 -> 0 | J126: =+J124/J$8 -> 0 | K126: =+K124/K$8 -> 0 | L126: =+L124/L$8 -> 0 | M126: =+M124/M$8 -> 0 | ... EG126: =+EG124/EG$8 -> 0
B128: Net Debtor Cash Flow (CET) | C128: [R$ k] | F128: =+F105+F115 -> -45 | G128: =+G105+G115 -> 0 | H128: =+H105+H115 -> 0 | I128: =+I105+I115 -> 0 | J128: =+J105+J115 -> 0 | K128: =+K105+K115 -> 0 | L128: =+L105+L115 -> 0 | M128: =+M105+M115 -> 0 | ... EG128: =+EG105+EG115 -> 0
B129: IPCA + Cash Flow | C129: [R$ k] | F129: =+F128/F$10 -> -45 | G129: =+G128/G$10 -> 0 | H129: =+H128/H$10 -> 0 | I129: =+I128/I$10 -> 0 | J129: =+J128/J$10 -> 0 | K129: =+K128/K$10 -> 0 | L129: =+L128/L$10 -> 0 | M129: =+M128/M$10 -> 0 | ... EG129: =+EG128/EG$10 -> 0
B130: CDI + Cash Flow | C130: [R$ k] | F130: =+F128/F$8 -> -45 | G130: =+G128/G$8 -> 0 | H130: =+H128/H$8 -> 0 | I130: =+I128/I$8 -> 0 | J130: =+J128/J$8 -> 0 | K130: =+K128/K$8 -> 0 | L130: =+L128/L$8 -> 0 | M130: =+M128/M$8 -> 0 | ... EG130: =+EG128/EG$8 -> 0
B133: Returns Summary | C133: FIDC | D133: Debtor | E133: CET
...

Sheet >

Sheet Comparativo RTD
B2: Comparativo RTD 2026 – CCB e Cessão Fiduciária (RJ x SP)
B4: Premissas
B5: RJ: CCB e cessão fiduciária tratadas como 2 registros separados de título/documento com valor declarado.
B6: SP: CCB na tabela de documentos com conteúdo financeiro; garantia fiduciária estimada por proxy do item de alienação fiduciária/leasing/reserva de domínio.
B7: Valores não incluem certidões, notificações, busca, páginas/vias extras ou despesas acessórias.
B9: Valor da CCB | C9: RJ – CCB | D9: RJ – cessão fiduciária | E9: RJ – total | F9: RJ – total % | G9: SP – CCB | H9: SP – garantia fiduciária | I9: SP – total | J9: SP – total %
B10: 10000 | C10: 650.69 | D10: 650.69 | E10: =C10+D10 -> 1301.38 | F10: =+E10/$B10 -> 0.130138 | G10: 404.56 | H10: 199.72 | I10: =G10+H10 -> 604.28 | J10: =+I10/$B10 -> 0.060428
B11: 20000 | C11: 976.85 | D11: 976.85 | E11: =C11+D11 -> 1953.7 | F11: =+E11/$B11 -> 0.097685 | G11: 614.96 | H11: 199.72 | I11: =G11+H11 -> 814.68 | J11: =+I11/$B11 -> 0.040734
B12: 30000 | C12: 1503.1 | D12: 1503.1 | E12: =C12+D12 -> 3006.2 | F12: =+E12/$B12 -> 0.10020667 | G12: 815.33 | H12: 199.72 | I12: =G12+H12 -> 1015.05 | J12: =+I12/$B12 -> 0.033835
B13: 40000 | C13: 2004.13 | D13: 2004.13 | E13: =C13+D13 -> 4008.26 | F13: =+E13/$B13 -> 0.1002065 | G13: 1015.71 | H13: 292.68 | I13: =G13+H13 -> 1308.39 | J13: =+I13/$B13 -> 0.03270975
B14: 50000 | C14: 2505.18 | D14: 2505.18 | E14: =C14+D14 -> 5010.36 | F14: =+E14/$B14 -> 0.1002072 | G14: 1015.71 | H14: 292.68 | I14: =G14+H14 -> 1308.39 | J14: =+I14/$B14 -> 0.0261678
B15: 60000 | C15: 2505.18 | D15: 2505.18 | E15: =C15+D15 -> 5010.36 | F15: =+E15/$B15 -> 0.083506 | G15: 1135.94 | H15: 292.68 | I15: =G15+H15 -> 1428.62 | J15: =+I15/$B15 -> 0.023810333
B16: 70000 | C16: 2806.13 | D16: 2806.13 | E16: =C16+D16 -> 5612.26 | F16: =+E16/$B16 -> 0.080175143 | G16: 1135.94 | H16: 292.68 | I16: =G16+H16 -> 1428.62 | J16: =+I16/$B16 -> 0.020408857
B17: 80000 | C17: 2806.13 | D17: 2806.13 | E17: =C17+D17 -> 5612.26 | F17: =+E17/$B17 -> 0.07015325 | G17: 1216.1 | H17: 385.63 | I17: =G17+H17 -> 1601.73 | J17: =+I17/$B17 -> 0.020021625
B18: 90000 | C18: 3007.8 | D18: 3007.8 | E18: =C18+D18 -> 6015.6 | F18: =+E18/$B18 -> 0.06684 | G18: 1216.1 | H18: 385.63 | I18: =G18+H18 -> 1601.73 | J18: =+I18/$B18 -> 0.017797
B19: 100000 | C19: 3007.8 | D19: 3007.8 | E19: =C19+D19 -> 6015.6 | F19: =+E19/$B19 -> 0.060156 | G19: 1296.24 | H19: 385.63 | I19: =G19+H19 -> 1681.87 | J19: =+I19/$B19 -> 0.0168187
B22: Observações
B23: Em RJ, a tabela consultada prevê desmembramento quando houver dois negócios jurídicos no mesmo documento.
B24: Em SP, o enquadramento de cessão fiduciária pode variar na prática do cartório; por isso o valor é estimativo.
B25: Fontes: RJ 4º RTD-RJ tabela 2026; SP CDT/RTD-SP tabela 2026.

Sheet Custo de Crédito BR
A1: Crédito PF — taxa média de juros e ICC (jan/2026)
A2: Tabela refeita com a nomenclatura corrigida: a coluna de custo agregado é ICC, não CET.
A4: Modalidade | B4: Série BCB usada | C4: Taxa média de juros (% a.a.) | D4: ICC (% a.a.) | E4: Observação
A5: Consignado público | B5: Crédito pessoal consignado – trabalhadores do setor público | C5: 0.2372 | D5: 0.2288 | E5: Sem proxy adicional.
A6: Consignado privado | B6: Crédito pessoal consignado – trabalhadores do setor privado | C6: 0.5736 | D6: 0.5157 | E6: Sem proxy adicional.
A7: Crédito clean | B7: Crédito pessoal não consignado | C7: 1.1813 | D7: 1.0039 | E7: Proxy BCB usado para “crédito clean”: crédito pessoal não consignado.
A8: Crédito com garantia em automóveis | B8: Aquisição de veículos | C8: 0.2771 | D8: 0.2696 | E8: Proxy BCB usado para “garantia em automóveis”: aquisição de veículos.
A11: Notas importantes
A12: • ICC = custo médio das operações em aberto na carteira; não é o CET contratual da operação individual.
A13: • Pela Resolução CMN 4.881/2020, o CET é uma taxa anual da operação individual e consolida juros, tarifas, tributos, seguros e outras despesas vinculadas.
A14: • “Crédito clean” foi aproximado pela série oficial do BCB de crédito pessoal não consignado.
A15: • “Crédito com garantia em automóveis” foi aproximado pela série oficial do BCB de aquisição de veículos.
A16: • Último dado usado nas séries: jan/2026.
A18: As URLs e os códigos das séries estão na aba “Base e fontes”.
A21: Base e fontes da tabela principal
A22: Os valores abaixo replicam o último ponto disponível (jan/2026) das séries públicas do Banco Central do Brasil.
A23: Modalidade | B23: Série BCB usada | C23: SGS juros | D23: Taxa média de juros (% a.a.) | E23: URL juros | F23: SGS ICC | G23: ICC (% a.a.) | H23: URL ICC | I23: Fonte conceitual | J23: Observação
A24: Consignado público | B24: Crédito pessoal consignado – trabalhadores do setor público | C24: 20745 | D24: 0.2372 | E24: https://api.bcb.gov.br/dados/serie/bcdata.sgs.20745/dados?formato=json | F24: 27676 | G24: 0.2288 | H24: https://api.bcb.gov.br/dados/serie/bcdata.sgs.27676/dados?formato=json | I24: https://opendata.bcb.gov.br/dataset/27676-average-cost-of-outstanding-loans---nonearmarked---households---payroll-deducted-personal-loa | J24: Sem proxy adicional.
A25: Consignado privado | B25: Crédito pessoal consignado – trabalhadores do setor privado | C25: 20744 | D25: 0.5736 | E25: https://api.bcb.gov.br/dados/serie/bcdata.sgs.20744/dados?formato=json | F25: 27675 | G25: 0.5157 | H25: https://api.bcb.gov.br/dados/serie/bcdata.sgs.27675/dados?formato=json | I25: https://opendata.bcb.gov.br/dataset/27675-average-cost-of-outstanding-loans---nonearmarked---households---payroll-deducted-personal-loa | J25: Sem proxy adicional.
A26: Crédito clean | B26: Crédito pessoal não consignado | C26: 20742 | D26: 1.1813 | E26: https://api.bcb.gov.br/dados/serie/bcdata.sgs.20742/dados?formato=json | F26: 27673 | G26: 1.0039 | H26: https://api.bcb.gov.br/dados/serie/bcdata.sgs.27673/dados?formato=json | I26: https://opendata.bcb.gov.br/dataset/27673-average-cost-of-outstanding-loans---nonearmarked---households---personal-credit | J26: Proxy BCB usado para “crédito clean”: crédito pessoal não consignado.
A27: Crédito com garantia em automóveis | B27: Aquisição de veículos | C27: 20749 | D27: 0.2771 | E27: https://api.bcb.gov.br/dados/serie/bcdata.sgs.20749/dados?formato=json | F27: 27680 | G27: 0.2696 | H27: https://api.bcb.gov.br/dados/serie/bcdata.sgs.27680/dados?formato=json | I27: https://opendata.bcb.gov.br/ne/dataset/27680-average-cost-of-outstanding-loans---nonearmarked---households---vehicles-financing | J27: Proxy BCB usado para “garantia em automóveis”: aquisição de veículos.
A29: Referência normativa para CET: https://www.bcb.gov.br/content/estabilidadefinanceira/especialnor/Resolu%C3%A7%C3%A3o4881.pdf
A32: Definições rápidas
A33: Termo | B33: Resumo | C33: URL
A34: CET | B34: Pela Resolução CMN 4.881/2020, o CET é uma taxa anual da operação individual que consolida juros, tarifas, tributos, seguros e outras despesas vinculadas. | C34: https://www.bcb.gov.br/content/estabilidadefinanceira/especialnor/Resolu%C3%A7%C3%A3o4881.pdf
A35: ICC | B35: Nas séries do BCB, o ICC é o custo médio das operações em aberto na carteira. É útil como visão agregada de custo, mas não substitui o CET contratual de cada operação. | C35: https://opendata.bcb.gov.br/dataset/27676-average-cost-of-outstanding-loans---nonearmarked---households---payroll-deducted-personal-loa
A36: Juros médios | B36: As séries de taxa média de juros refletem novas operações contratadas no período e são ponderadas pelo valor das concessões. | C36: https://dadosabertos.bcb.gov.br/dataset/20745-taxa-media-de-juros-das-operacoes-de-credito-com-recursos-livres---pessoas-fisicas---credito-
A37: Leitura correta da tabela | B37: A comparação abaixo é entre uma visão de fluxo (taxa média de juros das novas concessões) e uma visão de estoque/carteira (ICC). Por isso, a coluna de ICC não deve ser lida como CET. | C37: https://www.bcb.gov.br/content/estabilidadefinanceira/especialnor/Resolu%C3%A7%C3%A3o4881.pdf

Sheet >>

Sheet Macro
B7: Reference Date | C7: [date EoP] | D7: 46093
B8: Senior Tranche Interest | C8: [CDI + %] | D8: =Summary!#REF! -> #REF!
B9: Mezzanine Tranche Interest | C9: [CDI + %] | D9: =Summary!#REF! -> #REF!
J10: IPCA | N10: Selic
D11: Senior | E11: Mez
B12: Date | C12: CDI % p.m. | D12: CDI + % p.m. | E12: CDI + % p.m. | F12: IPCA | J12: Data | K12: Vértices | L12: Inflação Implícita | N12: Data | O12: Dias Corridos | P12: Preço/Taxa
B13: 44742 | C13: 0.01013541 | J13: =+$D$7+K13 -> 46219 | K13: 126 | L13: 0.039974 | N13: =+$D$7+O13 -> 46094 | O13: 1 | P13: 0.149
B14: 44773 | C14: 0.01084387 | D14: =+(1+C14)*(1+D$8)^(NETWORKDAYS(WORKDAY(B13,1,holidays),B14,holidays)/252)-1 -> #REF! | E14: =+(1+C14)*(1+D$9)^(NETWORKDAYS(WORKDAY(B13,1,holidays),B14,holidays)/252)-1 -> #REF! | J14: =+$D$7+K14 -> 46345 | K14: 252 | L14: 0.044948 | N14: =+$D$7+O14 -> 46098 | O14: 5 | P14: 0.1476
B15: 44804 | C15: 0.01118005 | D15: =+(1+C15)*(1+D$8)^(NETWORKDAYS(WORKDAY(B14,1,holidays),B15,holidays)/252)-1 -> #REF! | E15: =+(1+C15)*(1+D$9)^(NETWORKDAYS(WORKDAY(B14,1,holidays),B15,holidays)/252)-1 -> #REF! | J15: =+$D$7+K15 -> 46471 | K15: 378 | L15: 0.047209 | N15: =+$D$7+O15 -> 46099 | O15: 6 | P15: 0.1474
B16: 44834 | C16: 0.01071982 | D16: =+(1+C16)*(1+D$8)^(NETWORKDAYS(WORKDAY(B15,1,holidays),B16,holidays)/252)-1 -> #REF! | E16: =+(1+C16)*(1+D$9)^(NETWORKDAYS(WORKDAY(B15,1,holidays),B16,holidays)/252)-1 -> #REF! | J16: =+$D$7+K16 -> 46597 | K16: 504 | L16: 0.048486 | N16: =+$D$7+O16 -> 46100 | O16: 7 | P16: 0.1473
B17: 44865 | C17: 0.01020676 | D17: =+(1+C17)*(1+D$8)^(NETWORKDAYS(WORKDAY(B16,1,holidays),B17,holidays)/252)-1 -> #REF! | E17: =+(1+C17)*(1+D$9)^(NETWORKDAYS(WORKDAY(B16,1,holidays),B17,holidays)/252)-1 -> #REF! | J17: =+$D$7+K17 -> 46723 | K17: 630 | L17: 0.049409 | N17: =+$D$7+O17 -> 46101 | O17: 8 | P17: 0.1473
B18: 44895 | C18: 0.01020676 | D18: =+(1+C18)*(1+D$8)^(NETWORKDAYS(WORKDAY(B17,1,holidays),B18,holidays)/252)-1 -> #REF! | E18: =+(1+C18)*(1+D$9)^(NETWORKDAYS(WORKDAY(B17,1,holidays),B18,holidays)/252)-1 -> #REF! | J18: =+$D$7+K18 -> 46849 | K18: 756 | L18: 0.050243 | N18: =+$D$7+O18 -> 46102 | O18: 9 | P18: 0.1472
B19: 44926 | C19: 0.01174673 | D19: =+(1+C19)*(1+D$8)^(NETWORKDAYS(WORKDAY(B18,1,holidays),B19,holidays)/252)-1 -> #REF! | E19: =+(1+C19)*(1+D$9)^(NETWORKDAYS(WORKDAY(B18,1,holidays),B19,holidays)/252)-1 -> #REF! | J19: =+$D$7+K19 -> 46975 | K19: 882 | L19: 0.051089 | N19: =+$D$7+O19 -> 46105 | O19: 12 | P19: 0.1472
B20: 44957 | C20: 0.01071982 | D20: =+(1+C20)*(1+D$8)^(NETWORKDAYS(WORKDAY(B19,1,holidays),B20,holidays)/252)-1 -> #REF! | E20: =+(1+C20)*(1+D$9)^(NETWORKDAYS(WORKDAY(B19,1,holidays),B20,holidays)/252)-1 -> #REF! | J20: =+$D$7+K20 -> 47101 | K20: 1008 | L20: 0.051972 | N20: =+$D$7+O20 -> 46107 | O20: 14 | P20: 0.1471
B21: 44985 | C21: 0.00918141 | D21: =+(1+C21)*(1+D$8)^(NETWORKDAYS(WORKDAY(B20,1,holidays),B21,holidays)/252)-1 -> #REF! | E21: =+(1+C21)*(1+D$9)^(NETWORKDAYS(WORKDAY(B20,1,holidays),B21,holidays)/252)-1 -> #REF! | J21: =+$D$7+K21 -> 47227 | K21: 1134 | L21: 0.05288 | N21: =+$D$7+O21 -> 46109 | O21: 16 | P21: 0.1471
B22: 45016 | C22: 0.01174673 | D22: =+(1+C22)*(1+D$8)^(NETWORKDAYS(WORKDAY(B21,1,holidays),B22,holidays)/252)-1 -> #REF! | E22: =+(1+C22)*(1+D$9)^(NETWORKDAYS(WORKDAY(B21,1,holidays),B22,holidays)/252)-1 -> #REF! | J22: =+$D$7+K22 -> 47353 | K22: 1260 | L22: 0.053793 | N22: =+$D$7+O22 -> 46112 | O22: 19 | P22: 0.1471
B23: 45046 | C23: 0.00969396 | D23: =+(1+C23)*(1+D$8)^(NETWORKDAYS(WORKDAY(B22,1,holidays),B23,holidays)/252)-1 -> #REF! | E23: =+(1+C23)*(1+D$9)^(NETWORKDAYS(WORKDAY(B22,1,holidays),B23,holidays)/252)-1 -> #REF! | J23: =+$D$7+K23 -> 47479 | K23: 1386 | L23: 0.054686 | N23: =+$D$7+O23 -> 46113 | O23: 20 | P23: 0.1471
B24: 45077 | C24: 0.01071982 | D24: =+(1+C24)*(1+D$8)^(NETWORKDAYS(WORKDAY(B23,1,holidays),B24,holidays)/252)-1 -> #REF! | E24: =+(1+C24)*(1+D$9)^(NETWORKDAYS(WORKDAY(B23,1,holidays),B24,holidays)/252)-1 -> #REF! | J24: =+$D$7+K24 -> 47605 | K24: 1512 | L24: 0.05554 | N24: =+$D$7+O24 -> 46114 | O24: 21 | P24: 0.1471
B25: 45107 | C25: 0.01071982 | D25: =+(1+C25)*(1+D$8)^(NETWORKDAYS(WORKDAY(B24,1,holidays),B25,holidays)/252)-1 -> #REF! | E25: =+(1+C25)*(1+D$9)^(NETWORKDAYS(WORKDAY(B24,1,holidays),B25,holidays)/252)-1 -> #REF! | J25: =+$D$7+K25 -> 47731 | K25: 1638 | L25: 0.056339 | N25: =+$D$7+O25 -> 46123 | O25: 30 | P25: 0.1466
... B30: 45260 | C30: 0.00917769 | D30: =+(1+C30)*(1+D$8)^(NETWORKDAYS(WORKDAY(B29,1,holidays),B30,holidays)/252)-1 -> #REF! | E30: =+(1+C30)*(1+D$9)^(NETWORKDAYS(WORKDAY(B29,1,holidays),B30,holidays)/252)-1 -> #REF! | J30: =+$D$7+K30 -> 48361 | K30: 2268 | L30: 0.059282 | N30: =+$D$7+O30 -> 46130 | O30: 37 | P30: 0.1464
B31: 45291 | C31: 0.00940445 | D31: =+(1+C31)*(1+D$8)^(NETWORKDAYS(WORKDAY(B30,1,holidays),B31,holidays)/252)-1 -> #REF! | E31: =+(1+C31)*(1+D$9)^(NETWORKDAYS(WORKDAY(B30,1,holidays),B31,holidays)/252)-1 -> #REF! | J31: =+$D$7+K31 -> 48487 | K31: =+K30+($K$30-$K$29) -> 2394 | L31: =+L30 -> 0.059282 | N31: =+$D$7+O31 -> 46137 | O31: 44 | P31: 0.1463
B32: 45322 | C32: 0.00922548 | D32: =+(1+C32)*(1+D$8)^(NETWORKDAYS(WORKDAY(B31,1,holidays),B32,holidays)/252)-1 -> #REF! | E32: =+(1+C32)*(1+D$9)^(NETWORKDAYS(WORKDAY(B31,1,holidays),B32,holidays)/252)-1 -> #REF! | J32: =+$D$7+K32 -> 48613 | K32: =+K31+($K$30-$K$29) -> 2520 | L32: =+L31 -> 0.059282 | N32: =+$D$7+O32 -> 46141 | O32: 48 | P32: 0.1462
B33: 45351 | C33: 0.00801996 | D33: =+(1+C33)*(1+D$8)^(NETWORKDAYS(WORKDAY(B32,1,holidays),B33,holidays)/252)-1 -> #REF! | E33: =+(1+C33)*(1+D$9)^(NETWORKDAYS(WORKDAY(B32,1,holidays),B33,holidays)/252)-1 -> #REF! | J33: =+$D$7+K33 -> 48739 | K33: =+K32+($K$30-$K$29) -> 2646 | L33: =+L32 -> 0.059282 | N33: =+$D$7+O33 -> 46142 | O33: 49 | P33: 0.1462
B34: 45382 | C34: 0.0087398 | D34: =+(1+C34)*(1+D$8)^(NETWORKDAYS(WORKDAY(B33,1,holidays),B34,holidays)/252)-1 -> #REF! | E34: =+(1+C34)*(1+D$9)^(NETWORKDAYS(WORKDAY(B33,1,holidays),B34,holidays)/252)-1 -> #REF! | J34: =+$D$7+K34 -> 48865 | K34: =+K33+($K$30-$K$29) -> 2772 | L34: =+L33 -> 0.059282 | N34: =+$D$7+O34 -> 46143 | O34: 50 | P34: 0.1462
B35: 45412 | C35: 0.00846925 | D35: =+(1+C35)*(1+D$8)^(NETWORKDAYS(WORKDAY(B34,1,holidays),B35,holidays)/252)-1 -> #REF! | E35: =+(1+C35)*(1+D$9)^(NETWORKDAYS(WORKDAY(B34,1,holidays),B35,holidays)/252)-1 -> #REF! | J35: =+$D$7+K35 -> 48991 | K35: =+K34+($K$30-$K$29) -> 2898 | L35: =+L34 -> 0.059282 | N35: =+$D$7+O35 -> 46147 | O35: 54 | P35: 0.1461
B36: 45443 | C36: 0.00833347 | D36: =+(1+C36)*(1+D$8)^(NETWORKDAYS(WORKDAY(B35,1,holidays),B36,holidays)/252)-1 -> #REF! | E36: =+(1+C36)*(1+D$9)^(NETWORKDAYS(WORKDAY(B35,1,holidays),B36,holidays)/252)-1 -> #REF! | J36: =+$D$7+K36 -> 49117 | K36: =+K35+($K$30-$K$29) -> 3024 | L36: =+L35 -> 0.059282 | N36: =+$D$7+O36 -> 46154 | O36: 61 | P36: 0.1456
B37: 45473 | C37: 0.00827917 | D37: =+(1+C37)*(1+D$8)^(NETWORKDAYS(WORKDAY(B36,1,holidays),B37,holidays)/252)-1 -> #REF! | E37: =+(1+C37)*(1+D$9)^(NETWORKDAYS(WORKDAY(B36,1,holidays),B37,holidays)/252)-1 -> #REF! | J37: =+$D$7+K37 -> 49243 | K37: =+K36+($K$30-$K$29) -> 3150 | L37: =+L36 -> 0.059282 | N37: =+$D$7+O37 -> 46156 | O37: 63 | P37: 0.1455
B38: 45504 | C38: 0.00867512 | D38: =+(1+C38)*(1+D$8)^(NETWORKDAYS(WORKDAY(B37,1,holidays),B38,holidays)/252)-1 -> #REF! | E38: =+(1+C38)*(1+D$9)^(NETWORKDAYS(WORKDAY(B37,1,holidays),B38,holidays)/252)-1 -> #REF! | J38: =+$D$7+K38 -> 49369 | K38: =+K37+($K$30-$K$29) -> 3276 | L38: =+L37 -> 0.059282 | N38: =+$D$7+O38 -> 46158 | O38: 65 | P38: 0.1453
B39: 45535 | C39: 0.00907122 | D39: =+(1+C39)*(1+D$8)^(NETWORKDAYS(WORKDAY(B38,1,holidays),B39,holidays)/252)-1 -> #REF! | E39: =+(1+C39)*(1+D$9)^(NETWORKDAYS(WORKDAY(B38,1,holidays),B39,holidays)/252)-1 -> #REF! | J39: =+$D$7+K39 -> 49495 | K39: =+K38+($K$30-$K$29) -> 3402 | L39: =+L38 -> 0.059282 | N39: =+$D$7+O39 -> 46162 | O39: 69 | P39: 0.1452
B40: 45565 | C40: 0.0079467 | D40: =+(1+C40)*(1+D$8)^(NETWORKDAYS(WORKDAY(B39,1,holidays),B40,holidays)/252)-1 -> #REF! | E40: =+(1+C40)*(1+D$9)^(NETWORKDAYS(WORKDAY(B39,1,holidays),B40,holidays)/252)-1 -> #REF! | J40: =+$D$7+K40 -> 49621 | K40: =+K39+($K$30-$K$29) -> 3528 | L40: =+L39 -> 0.059282 | N40: =+$D$7+O40 -> 46163 | O40: 70 | P40: 0.1451
B41: 45596 | C41: 0.00927958 | D41: =+(1+C41)*(1+D$8)^(NETWORKDAYS(WORKDAY(B40,1,holidays),B41,holidays)/252)-1 -> #REF! | E41: =+(1+C41)*(1+D$9)^(NETWORKDAYS(WORKDAY(B40,1,holidays),B41,holidays)/252)-1 -> #REF! | J41: =+$D$7+K41 -> 49747 | K41: =+K40+($K$30-$K$29) -> 3654 | L41: =+L40 -> 0.059282 | N41: =+$D$7+O41 -> 46164 | O41: 71 | P41: 0.145
B42: 45626 | C42: 0.00833477 | D42: =+(1+C42)*(1+D$8)^(NETWORKDAYS(WORKDAY(B41,1,holidays),B42,holidays)/252)-1 -> #REF! | E42: =+(1+C42)*(1+D$9)^(NETWORKDAYS(WORKDAY(B41,1,holidays),B42,holidays)/252)-1 -> #REF! | J42: =+$D$7+K42 -> 49873 | K42: =+K41+($K$30-$K$29) -> 3780 | L42: =+L41 -> 0.059282 | N42: =+$D$7+O42 -> 46170 | O42: 77 | P42: 0.1448
... B55: 46022 | C55: 0.01164123 | D55: =+(1+C55)*(1+D$8)^(NETWORKDAYS(WORKDAY(B54,1,holidays),B55,holidays)/252)-1 -> #REF! | E55: =+(1+C55)*(1+D$9)^(NETWORKDAYS(WORKDAY(B54,1,holidays),B55,holidays)/252)-1 -> #REF! | J55: =+$D$7+K55 -> 51511 | K55: =+K54+($K$30-$K$29) -> 5418 | L55: =+L54 -> 0.059282 | N55: =+$D$7+O55 -> 46213 | O55: 120 | P55: 0.143
B56: 46053 | C56: =+(1+_xlfn.XLOOKUP(B56,$N$13:$N$301,$P$13:$P$301,,1))^(1/12)-1 -> 0.011641575 | D56: =+(1+C56)*(1+D$8)^(1/12)-1 -> #REF! | E56: =+(1+C56)*(1+D$9)^(1/12)-1 -> #REF! | F56: =+_xlfn.XLOOKUP(B56,$J$13:$J$57,$L$13:$L$57,,1) -> 0.039974 | J56: =+$D$7+K56 -> 51637 | K56: =+K55+($K$30-$K$29) -> 5544 | L56: =+L55 -> 0.059282 | N56: =+$D$7+O56 -> 46218 | O56: 125 | P56: 0.1428
B57: 46081 | C57: =+(1+_xlfn.XLOOKUP(B57,$N$13:$N$301,$P$13:$P$301,,1))^(1/12)-1 -> 0.011641575 | D57: =+(1+C57)*(1+D$8)^(1/12)-1 -> #REF! | E57: =+(1+C57)*(1+D$9)^(1/12)-1 -> #REF! | F57: =+_xlfn.XLOOKUP(B57,$J$13:$J$57,$L$13:$L$57,,1) -> 0.039974 | J57: =+$D$7+K57 -> 51763 | K57: =+K56+($K$30-$K$29) -> 5670 | L57: =+L56 -> 0.059282 | N57: =+$D$7+O57 -> 46219 | O57: 126 | P57: 0.1427
B58: 46112 | C58: =+(1+_xlfn.XLOOKUP(B58,$N$13:$N$301,$P$13:$P$301,,1))^(1/12)-1 -> 0.011502064 | D58: =+(1+C58)*(1+D$8)^(1/12)-1 -> #REF! | E58: =+(1+C58)*(1+D$9)^(1/12)-1 -> #REF! | F58: =+_xlfn.XLOOKUP(B58,$J$13:$J$57,$L$13:$L$57,,1) -> 0.039974 | N58: =+$D$7+O58 -> 46227 | O58: 134 | P58: 0.1424
B59: 46142 | C59: =+(1+_xlfn.XLOOKUP(B59,$N$13:$N$301,$P$13:$P$301,,1))^(1/12)-1 -> 0.011435906 | D59: =+(1+C59)*(1+D$8)^(1/12)-1 -> #REF! | E59: =+(1+C59)*(1+D$9)^(1/12)-1 -> #REF! | F59: =+_xlfn.XLOOKUP(B59,$J$13:$J$57,$L$13:$L$57,,1) -> 0.039974 | N59: =+$D$7+O59 -> 46234 | O59: 141 | P59: 0.1422
B60: 46173 | C60: =+(1+_xlfn.XLOOKUP(B60,$N$13:$N$301,$P$13:$P$301,,1))^(1/12)-1 -> 0.011318174 | D60: =+(1+C60)*(1+D$8)^(1/12)-1 -> #REF! | E60: =+(1+C60)*(1+D$9)^(1/12)-1 -> #REF! | F60: =+_xlfn.XLOOKUP(B60,$J$13:$J$57,$L$13:$L$57,,1) -> 0.039974 | N60: =+$D$7+O60 -> 46235 | O60: 142 | P60: 0.1421
B61: 46203 | C61: =+(1+_xlfn.XLOOKUP(B61,$N$13:$N$301,$P$13:$P$301,,1))^(1/12)-1 -> 0.011237146 | D61: =+(1+C61)*(1+D$8)^(1/12)-1 -> #REF! | E61: =+(1+C61)*(1+D$9)^(1/12)-1 -> #REF! | F61: =+_xlfn.XLOOKUP(B61,$J$13:$J$57,$L$13:$L$57,,1) -> 0.039974 | N61: =+$D$7+O61 -> 46238 | O61: 145 | P61: 0.1421
B62: 46234 | C62: =+(1+_xlfn.XLOOKUP(B62,$N$13:$N$301,$P$13:$P$301,,1))^(1/12)-1 -> 0.011141293 | D62: =+(1+C62)*(1+D$8)^(1/12)-1 -> #REF! | E62: =+(1+C62)*(1+D$9)^(1/12)-1 -> #REF! | F62: =+_xlfn.XLOOKUP(B62,$J$13:$J$57,$L$13:$L$57,,1) -> 0.044948 | N62: =+$D$7+O62 -> 46245 | O62: 152 | P62: 0.1417
B63: 46265 | C63: =+(1+_xlfn.XLOOKUP(B63,$N$13:$N$301,$P$13:$P$301,,1))^(1/12)-1 -> 0.011037955 | D63: =+(1+C63)*(1+D$8)^(1/12)-1 -> #REF! | E63: =+(1+C63)*(1+D$9)^(1/12)-1 -> #REF! | F63: =+_xlfn.XLOOKUP(B63,$J$13:$J$57,$L$13:$L$57,,1) -> 0.044948 | N63: =+$D$7+O63 -> 46247 | O63: 154 | P63: 0.1416
B64: 46295 | C64: =+(1+_xlfn.XLOOKUP(B64,$N$13:$N$301,$P$13:$P$301,,1))^(1/12)-1 -> 0.010949286 | D64: =+(1+C64)*(1+D$8)^(1/12)-1 -> #REF! | E64: =+(1+C64)*(1+D$9)^(1/12)-1 -> #REF! | F64: =+_xlfn.XLOOKUP(B64,$J$13:$J$57,$L$13:$L$57,,1) -> 0.044948 | N64: =+$D$7+O64 -> 46252 | O64: 159 | P64: 0.1414
B65: 46326 | C65: =+(1+_xlfn.XLOOKUP(B65,$N$13:$N$301,$P$13:$P$301,,1))^(1/12)-1 -> 0.010867932 | D65: =+(1+C65)*(1+D$8)^(1/12)-1 -> #REF! | E65: =+(1+C65)*(1+D$9)^(1/12)-1 -> #REF! | F65: =+_xlfn.XLOOKUP(B65,$J$13:$J$57,$L$13:$L$57,,1) -> 0.044948 | N65: =+$D$7+O65 -> 46253 | O65: 160 | P65: 0.1413
B66: 46356 | C66: =+(1+_xlfn.XLOOKUP(B66,$N$13:$N$301,$P$13:$P$301,,1))^(1/12)-1 -> 0.010801316 | D66: =+(1+C66)*(1+D$8)^(1/12)-1 -> #REF! | E66: =+(1+C66)*(1+D$9)^(1/12)-1 -> #REF! | F66: =+_xlfn.XLOOKUP(B66,$J$13:$J$57,$L$13:$L$57,,1) -> 0.047209 | N66: =+$D$7+O66 -> 46262 | O66: 169 | P66: 0.1409
B67: 46387 | C67: =+(1+_xlfn.XLOOKUP(B67,$N$13:$N$301,$P$13:$P$301,,1))^(1/12)-1 -> 0.010734651 | D67: =+(1+C67)*(1+D$8)^(1/12)-1 -> #REF! | E67: =+(1+C67)*(1+D$9)^(1/12)-1 -> #REF! | F67: =+_xlfn.XLOOKUP(B67,$J$13:$J$57,$L$13:$L$57,,1) -> 0.047209 | N67: =+$D$7+O67 -> 46263 | O67: 170 | P67: 0.1408
B68: 46418 | C68: =+(1+_xlfn.XLOOKUP(B68,$N$13:$N$301,$P$13:$P$301,,1))^(1/12)-1 -> 0.010675353 | D68: =+(1+C68)*(1+D$8)^(1/12)-1 -> #REF! | E68: =+(1+C68)*(1+D$9)^(1/12)-1 -> #REF! | F68: =+_xlfn.XLOOKUP(B68,$J$13:$J$57,$L$13:$L$57,,1) -> 0.047209 | N68: =+$D$7+O68 -> 46266 | O68: 173 | P68: 0.1408
B69: 46446 | C69: =+(1+_xlfn.XLOOKUP(B69,$N$13:$N$301,$P$13:$P$301,,1))^(1/12)-1 -> 0.010630855 | D69: =+(1+C69)*(1+D$8)^(1/12)-1 -> #REF! | E69: =+(1+C69)*(1+D$9)^(1/12)-1 -> #REF! | F69: =+_xlfn.XLOOKUP(B69,$J$13:$J$57,$L$13:$L$57,,1) -> 0.047209 | N69: =+$D$7+O69 -> 46267 | O69: 174 | P69: 0.1407
... B234: 51470 | C234: =+(1+_xlfn.XLOOKUP(B234,$N$13:$N$301,$P$13:$P$301,,1))^(1/12)-1 -> 0.010705007 | D234: =+(1+C234)*(1+D$8)^(1/12)-1 -> #REF! | E234: =+(1+C234)*(1+D$9)^(1/12)-1 -> #REF! | F234: =+_xlfn.XLOOKUP(B234,$J$13:$J$57,$L$13:$L$57,,1) -> 0.059282 | N234: =+$D$7+O234 -> 49537 | O234: 3444 | P234: 0.1363
B235: =+EOMONTH(B234,1) -> 51501 | C235: =+(1+_xlfn.XLOOKUP(B235,$N$13:$N$301,$P$13:$P$301,,1))^(1/12)-1 -> 0.010705007 | D235: =+(1+C235)*(1+D$8)^(1/12)-1 -> #REF! | E235: =+(1+C235)*(1+D$9)^(1/12)-1 -> #REF! | F235: =+_xlfn.XLOOKUP(B235,$J$13:$J$57,$L$13:$L$57,,1) -> 0.059282 | N235: =+$D$7+O235 -> 49630 | O235: 3537 | P235: 0.1363
B236: =+EOMONTH(B235,1) -> 51532 | C236: =+(1+_xlfn.XLOOKUP(B236,$N$13:$N$301,$P$13:$P$301,,1))^(1/12)-1 -> 0.010705007 | D236: =+(1+C236)*(1+D$8)^(1/12)-1 -> #REF! | E236: =+(1+C236)*(1+D$9)^(1/12)-1 -> #REF! | F236: =+_xlfn.XLOOKUP(B236,$J$13:$J$57,$L$13:$L$57,,1) -> 0.059282 | N236: =+$D$7+O236 -> 49677 | O236: 3584 | P236: 0.1362
N237: =+$D$7+O237 -> 49693 | O237: 3600 | P237: 0.1362
N238: =+$D$7+O238 -> 49721 | O238: 3628 | P238: 0.1363
N239: =+$D$7+O239 -> 49811 | O239: 3718 | P239: 0.1364
N240: =+$D$7+O240 -> 49903 | O240: 3810 | P240: 0.1365
N241: =+$D$7+O241 -> 49997 | O241: 3904 | P241: 0.1366
N242: =+$D$7+O242 -> 50043 | O242: 3950 | P242: 0.1366
N243: =+$D$7+O243 -> 50053 | O243: 3960 | P243: 0.1366
N244: =+$D$7+O244 -> 50090 | O244: 3997 | P244: 0.1366
N245: =+$D$7+O245 -> 50176 | O245: 4083 | P245: 0.1366
N246: =+$D$7+O246 -> 50270 | O246: 4177 | P246: 0.1366
N247: =+$D$7+O247 -> 50361 | O247: 4268 | P247: 0.1366
N248: =+$D$7+O248 -> 50410 | O248: 4317 | P248: 0.1366
... N301: =+$D$7+O301 -> 58670 | O301: 12577 | P301: 0.1369

Sheet Holidays
A1: Data | B1: Dia da Semana | C1: Feriado
A2: 36892 | B2: segunda-feira | C2: Confraternização Universal
A3: 36948 | B3: segunda-feira | C3: Carnaval
A4: 36949 | B4: terça-feira | C4: Carnaval
A5: 36994 | B5: sexta-feira | C5: Paixão de Cristo
A6: 37002 | B6: sábado | C6: Tiradentes
A7: 37012 | B7: terça-feira | C7: Dia do Trabalho
A8: 37056 | B8: quinta-feira | C8: Corpus Christi
A9: 37141 | B9: sexta-feira | C9: Independência do Brasil
A10: 37176 | B10: sexta-feira | C10: Nossa Sr.a Aparecida - Padroeira do Brasil
A11: 37197 | B11: sexta-feira | C11: Finados
A12: 37210 | B12: quinta-feira | C12: Proclamação da República
A13: 37250 | B13: terça-feira | C13: Natal
... A937: 65374 | B937: quarta-feira | C937: Natal
